Metadata-Version: 2.1
Name: wazuh-findings-exporter
Version: 1.0
Summary: Simple script that exports Wazuh Vulnerabilities by Agent groups
Home-page: https://github.com/quirinziessler/wazuh_findings_exporter
Download-URL: https://github.com/quirinziessler/wazuh_findings_exporter
Author: Quirin Hardy Zießler
Author-email: quirin@ziessler.com
License: MIT
Keywords: Wazuh,exporter,DefectDojo,Wazuh API
Classifier: Intended Audience :: Developers
Classifier: Topic :: Software Development :: Build Tools
Classifier: Programming Language :: Python :: 3
Classifier: Programming Language :: Python :: 3.6
Classifier: Programming Language :: Python :: 3.7
Classifier: Programming Language :: Python :: 3.8
Classifier: Programming Language :: Python :: 3.9
Classifier: Programming Language :: Python :: 3.11
License-File: LICENSE.txt
Requires-Dist: urllib3
Requires-Dist: requests
